setup.py
cybervpn/__init__.py
cybervpn/module.py
cybervpn.egg-info/PKG-INFO
cybervpn.egg-info/SOURCES.txt
cybervpn.egg-info/dependency_links.txt
cybervpn.egg-info/entry_points.txt
cybervpn.egg-info/requires.txt
cybervpn.egg-info/top_level.txt